rapoc/__about__.py
rapoc/__init__.py
rapoc/__version__.py
rapoc/loaders/__init__.py
rapoc/loaders/ciaHitranFileLoader.py
rapoc/loaders/daceFileLoader.py
rapoc/loaders/dictLoader.py
rapoc/loaders/exoMolFileLoader.py
rapoc/loaders/loader.py
rapoc/models/__init__.py
rapoc/models/model.py
rapoc/models/planck.py
rapoc/models/rayleigh.py
rapoc/models/rosseland.py
rapoc/models/validation.py
rapoc/models/utils/__init__.py
rapoc/models/utils/validation.py
rapoc-1.0.8.dist-info/LICENSE
rapoc-1.0.8.dist-info/METADATA
rapoc-1.0.8.dist-info/WHEEL
rapoc-1.0.8.dist-info/top_level.txt
rapoc-1.0.8.dist-info/RECORD
