Metadata-Version: 2.1
Name: rapoc
Version: 1.0.8
Summary: Rosseland And Planck Opacity Converter
Home-page: https://github.com/ExObsSim/Rapoc-public
Author: Lorenzo V. Mugnai, Darius Modirrousta-Galian
Author-email: lorenzo.mugnai@uniroma1.it
License: BSD-3-Clause
Classifier: Development Status :: 4 - Beta
Classifier: Intended Audience :: Developers
Classifier: Intended Audience :: Science/Research
Classifier: License :: OSI Approved :: BSD License
Classifier: Operating System :: POSIX
Classifier: Operating System :: POSIX :: Linux
Classifier: Operating System :: Unix
Classifier: Operating System :: OS Independent
Classifier: Programming Language :: Python :: 3
Classifier: Topic :: Scientific/Engineering
Classifier: Topic :: Software Development :: Libraries
Provides: rapoc
Requires-Python: >=3.8
License-File: LICENSE
Requires-Dist: astropy
Requires-Dist: matplotlib
Requires-Dist: numpy
Requires-Dist: scipy
Requires-Dist: h5py
Requires-Dist: molmass
Requires-Dist: tqdm
